uscalt_drf/__init__.py
uscalt_drf/admin.py
uscalt_drf/apps.py
uscalt_drf/models.py
uscalt_drf/serializers.py
uscalt_drf/urls.py
uscalt_drf/utils.py
uscalt_drf/views.py
uscalt_drf/migrations/0001_initial.py
uscalt_drf/migrations/0002_intentsilo.py
uscalt_drf/migrations/__init__.py
uscalt_drf-0.1.1.3.dist-info/LICENSE
uscalt_drf-0.1.1.3.dist-info/METADATA
uscalt_drf-0.1.1.3.dist-info/WHEEL
uscalt_drf-0.1.1.3.dist-info/top_level.txt
uscalt_drf-0.1.1.3.dist-info/RECORD
