Metadata-Version: 2.1
Name: uscalt-drf
Version: 0.1.1.3
Summary: A companion library for Uscalt made for Django Rest Framework
Home-page: https://github.com/JustCunn/uscalt-drf
Author: Justin Cunningham
Author-email: justinike.cunningham@outlook.com
License: UNKNOWN
Project-URL: Bug Tracker, https://github.com/JustCunn/uscalt-drf/issues
Platform: UNKNOWN
Classifier: Programming Language :: Python :: 3
Classifier: Operating System :: OS Independent
Classifier: Environment :: Web Environment
Classifier: Framework :: Django
Classifier: Intended Audience :: Developers
Classifier: License :: OSI Approved :: BSD License
Classifier: Operating System :: OS Independent
Classifier: Programming Language :: Python
Classifier: Topic :: Internet :: WWW/HTTP
Classifier: Topic :: Internet :: WWW/HTTP :: Dynamic Content
Requires-Python: >=3.6
License-File: LICENSE
Requires-Dist: Django (>=4.0)
Requires-Dist: djangorestframework (>=3.13)
